tbm/__init__.py
tbm/build.py
tbm/help.py
tbm/main.py
tbm/run.py
tbm-1.2.5.dist-info/METADATA
tbm-1.2.5.dist-info/WHEEL
tbm-1.2.5.dist-info/entry_points.txt
tbm-1.2.5.dist-info/top_level.txt
tbm-1.2.5.dist-info/RECORD
