Metadata-Version: 2.1
Name: tbm
Version: 1.2.5
Summary: telegram bot manager
Author: https://github.com/pousay
Author-email: pouryathesaymon@gmail.com
Requires-Dist: watchdog
Requires-Dist: inquirer
